LICENSE
MANIFEST.in
README
setup.cfg
setup.py
onyxbabel/__init__.py
onyxbabel/_compat.py
onyxbabel.egg-info/PKG-INFO
onyxbabel.egg-info/SOURCES.txt
onyxbabel.egg-info/dependency_links.txt
onyxbabel.egg-info/not-zip-safe
onyxbabel.egg-info/requires.txt
onyxbabel.egg-info/top_level.txt