Metadata-Version: 1.1
Name: onyxbabel
Version: 0.0.3
Summary: Ramake of the Flask_BabelEX for Onyx
Home-page: http://github.com/mrjoes/flask-babelex
Author: Serge S. Koval
Author-email: serge.koval+github@gmail.com
License: BSD
Platform: any
Classifier: Development Status :: 4 - Beta
Classifier: Environment :: Web Environment
Classifier: Intended Audience :: Developers
Classifier: License :: OSI Approved :: BSD License
Classifier: Operating System :: OS Independent
Classifier: Programming Language :: Python
Classifier: Programming Language :: Python :: 3
Classifier: Topic :: Internet :: WWW/HTTP :: Dynamic Content
Classifier: Topic :: Software Development :: Libraries :: Python Modules
